lsst/__init__.py
lsst/ctrl/__init__.py
lsst/ctrl/execute/__init__.py
lsst/ctrl/execute/allocationConfig.py
lsst/ctrl/execute/allocator.py
lsst/ctrl/execute/allocatorParser.py
lsst/ctrl/execute/condorConfig.py
lsst/ctrl/execute/condorInfoConfig.py
lsst/ctrl/execute/envString.py
lsst/ctrl/execute/findPackageFile.py
lsst/ctrl/execute/namedClassFactory.py
lsst/ctrl/execute/pbsPlugin.py
lsst/ctrl/execute/qCommand.py
lsst/ctrl/execute/seqFile.py
lsst/ctrl/execute/slurmPlugin.py
lsst/ctrl/execute/templateWriter.py
lsst/ctrl/execute/libexec/allocateNodes.py
lsst/ctrl/execute/libexec/dagIdInfo.py
lsst/ctrl/execute/libexec/qdelete.py
lsst/ctrl/execute/libexec/qstatus.py
lsst_ctrl_execute-30.0.0.dist-info/METADATA
lsst_ctrl_execute-30.0.0.dist-info/WHEEL
lsst_ctrl_execute-30.0.0.dist-info/entry_points.txt
lsst_ctrl_execute-30.0.0.dist-info/licenses/COPYRIGHT
lsst_ctrl_execute-30.0.0.dist-info/licenses/LICENSE
lsst_ctrl_execute-30.0.0.dist-info/licenses/bsd_license.txt
lsst_ctrl_execute-30.0.0.dist-info/licenses/gpl-v3.0.txt
lsst_ctrl_execute-30.0.0.dist-info/RECORD
