Metadata-Version: 2.4
Name: lsst-ctrl-execute
Version: 30.0.0
Summary: Utilities for executing and managing workloads.
Project-URL: Homepage, https://github.com/lsst/ctrl_execute
Author-email: Rubin Observatory Data Management <dm-admin@lists.lsst.org>
License-Expression: BSD-3-Clause OR GPL-3.0-or-later
License-File: COPYRIGHT
License-File: LICENSE
License-File: bsd_license.txt
License-File: gpl-v3.0.txt
Keywords: lsst
Classifier: Intended Audience :: Science/Research
Classifier: Operating System :: OS Independent
Classifier: Programming Language :: Python :: 3
Classifier: Programming Language :: Python :: 3.11
Classifier: Programming Language :: Python :: 3.12
Classifier: Programming Language :: Python :: 3.13
Classifier: Programming Language :: Python :: 3.14
Classifier: Topic :: Scientific/Engineering :: Astronomy
Requires-Python: >=3.11.0
Requires-Dist: htcondor==24.0.*
Requires-Dist: lsst-ctrl-bps-htcondor>=28.2024.5000; sys_platform == 'linux'
Requires-Dist: lsst-pex-config>=30.2026.300
Requires-Dist: lsst-resources>=30.2026.300
Requires-Dist: lsst-utils
